rfsspec-0.1.1.dist-info/METADATA
rfsspec-0.1.1.dist-info/WHEEL
rfsspec-0.1.1.dist-info/license_files/LICENSE
rfsspec.libs/libssl-6e87fb74.so.3
rfsspec.libs/libcrypto-a8823a56.so.3
rfsspec/gcs.py
rfsspec/__init__.py
rfsspec/http.py
rfsspec/azure.py
rfsspec/s3.py
rfsspec/rfsspec.cpython-39-x86_64-linux-gnu.so
rfsspec-0.1.1.dist-info/RECORD
