Metadata-Version: 2.1
Name: rfsspec
Version: 0.1.1
Classifier: Programming Language :: Rust
Classifier: Programming Language :: Python :: Implementation :: CPython
Requires-Dist: fsspec >=2023
License-File: LICENSE
Requires-Python: >=3.8
